<?xml version="1.0" encoding="UTF-8"?>
<!DOCTYPE dataset SYSTEM "data.dtd">
<!-- Auto-generated by the Maven Impex Plugin -->
<dataset>
	<KSEN_ATP_NAME ID="" LOCALE="en" NAME="" OBJ_ID="" OWNER="" />
	<KSEN_ATP_NAME ID="" LOCALE="en" NAME="2010-2011 Academic 
		Year"
		OBJ_ID="" OWNER="AcademicCalendar20102011" />
	<KSEN_ATP_NAME ID="" LOCALE="en" NAME="Spring 2011"
		OBJ_ID="" OWNER="Spring2011" />
	<KSEN_ATP_NAME ID="" LOCALE="en" NAME="testingAcal1"
		OBJ_ID="" OWNER="termRelationTestingAcal1" />
	<KSEN_ATP_NAME ID="" LOCALE="en" NAME="testingAcal2"
		OBJ_ID="" OWNER="termRelationTestingAcal2" />
	<KSEN_ATP_NAME ID="" LOCALE="en" NAME="testingTerm1"
		OBJ_ID="" OWNER="termRelationTestingTerm1" />
	<KSEN_ATP_NAME ID="" LOCALE="en" NAME="testingTerm2"
		OBJ_ID="" OWNER="termRelationTestingTerm2" />
	<KSEN_ATP_NAME ID="" LOCALE="en" NAME="testingTerm3"
		OBJ_ID="" OWNER="termRelationTestingTerm3" />
	<KSEN_ATP_NAME ID="" LOCALE="en" NAME="testingTerm4"
		OBJ_ID="" OWNER="termRelationTestingTerm4" />
	<KSEN_ATP_NAME ID="" LOCALE="en" NAME="testingTerm3"
		OBJ_ID="" OWNER="termRelationTestingTerm5" />
	<KSEN_ATP_NAME ID="" LOCALE="en" NAME="testingTerm4"
		OBJ_ID="" OWNER="termRelationTestingTerm6" />
	<KSEN_ATP_NAME ID="" LOCALE="en" NAME="testingTermDelete"
		OBJ_ID="" OWNER="termRelationTestingTermDelete" />
	<KSEN_ATP_NAME ID="" LOCALE="en" NAME="2011-2012 Academic Year"
		OBJ_ID="" OWNER="testAtpId1" />
	<KSEN_ATP_NAME ID="" LOCALE="en" NAME="2011-2012 Holiday Calendar"
		OBJ_ID="" OWNER="testAtpId2" />
	<KSEN_ATP_NAME ID="" LOCALE="en" NAME="testDeleteAtp1"
		OBJ_ID="" OWNER="testDeleteAtpId1" />
	<KSEN_ATP_NAME ID="" LOCALE="en" NAME="testDeleteAtp2"
		OBJ_ID="" OWNER="testDeleteAtpId2" />
	<KSEN_ATP_NAME ID="" LOCALE="en" NAME="Fall 2010" OBJ_ID=""
		OWNER="testTermId0" />
	<KSEN_ATP_NAME ID="" LOCALE="en" NAME="Fall 2011" OBJ_ID=""
		OWNER="testTermId1" />
	<KSEN_ATP_NAME ID="" LOCALE="en" NAME="" OBJ_ID=""
		OWNER="testTermId2" />
	<KSEN_ATP_NAME ID="" LOCALE="en" NAME="" OBJ_ID=""
		OWNER="testTermId3" />
	<KSEN_ATP_NAME ID="" LOCALE="en" NAME="Summer 2012"
		OBJ_ID="" OWNER="testTermId4" />
</dataset>
