<?xml version="1.0" encoding="UTF-8"?>
<!--

    Copyright 2005-2013 The Kuali Foundation

    Licensed under the Educational Community License, Version 2.0 (the "License");
    you may not use this file except in compliance with the License.
    You may obtain a copy of the License at

    http://www.opensource.org/licenses/ecl2.php

    Unless required by applicable law or agreed to in writing, software
    distributed under the License is distributed on an "AS IS" BASIS,
    WITHOUT WARRANTIES OR CONDITIONS OF ANY KIND, either express or implied.
    See the License for the specific language governing permissions and
    limitations under the License.

-->
<beans xmlns="http://www.springframework.org/schema/beans" xmlns:p="http://www.springframework.org/schema/p" xmlns:xsi="http://www.w3.org/2001/XMLSchema-instance" xsi:schemaLocation="http://www.springframework.org/schema/beans         http://www.springframework.org/schema/beans/spring-beans-2.0.xsd">  
  <bean id="OrgPositionRestrictionInfoAdmin-MaintenanceView" parent="Uif-MaintenanceView">
  	<property name="headerText" value="OrgPositionRestrictionInfoAdmin Maintenance"/>
   	<property name="dataObjectClassName" value="org.kuali.student.r2.core.organization.dto.OrgPositionRestrictionInfo"/>
    <property name="items">
      <list>
        <bean parent="Uif-MaintenanceGridSection">
          <property name="headerText" value="Create a New OrgPositionRestrictionInfoAdmin"/>
          <property name="items">
            <list>
              <bean parent="Uif-InputField" p:propertyName="id" p:readOnly="true"/>
              <bean parent="Uif-InputField" p:propertyName="orgId" >
              	<property name="quickfinder.dataObjectClassName" value="org.kuali.student.r2.core.organization.dto.OrgInfo"/>
                <property name="quickfinder.fieldConversions">
                   <map>
                       <entry key="id" value="orgId"/>
                   </map>
                </property>                  
              </bean>
              <bean parent="Uif-InputField" p:propertyName="orgPersonRelationTypeKey" />
			  <bean parent="Uif-InputField" p:propertyName="title" />			 
              <bean parent="Uif-InputField" p:propertyName="stdDuration.atpDurationTypeKey" >
              	<property name="quickfinder.dataObjectClassName" value="org.kuali.student.r2.core.class1.type.dto.TypeInfo"/>
                <property name="quickfinder.fieldConversions">
                   <map>
                       <entry key="key" value="stdDuration.atpDurationTypeKey"/>
                   </map>
                </property>                  
              </bean>   
              <bean parent="Uif-InputField" p:propertyName="stdDuration.timeQuantity" />
              <bean parent="Uif-InputField" p:propertyName="minNumRelations" />
              <bean parent="Uif-InputField" p:propertyName="maxNumRelations" />              		                  	
            </list>
          </property>
        </bean>        
      </list>
    </property>
  </bean>
  <bean id="OrgPositionRestrictionInfoAdminMaintenanceDocument" parent="OrgPositionRestrictionInfoAdminMaintenanceDocument-parentBean"/>
  <bean id="OrgPositionRestrictionInfoAdminMaintenanceDocument-parentBean" abstract="true" parent="uifMaintenanceDocumentEntry">
    <property name="dataObjectClass" value="org.kuali.student.r2.core.organization.dto.OrgPositionRestrictionInfo"/>
    <property name="maintainableClass" value="org.kuali.student.core.ui.admin.organization.OrgPositionRestrictionInfoAdminMaintainableImpl"/>
    <property name="businessRulesClass" value="org.kuali.student.core.ui.admin.organization.rule.OrgPositionRestrictionInfoAdminRule"/>
    <property name="documentTypeName" value="OrgPositionRestrictionInfoAdminMaintenanceDocument"/>
     <property name="lockingKeys">
        <list>
            <value>id</value>
        </list>
    </property>
  </bean>
</beans>