<databaseChangeLog xmlns="http://www.liquibase.org/xml/ns/dbchangelog" xmlns:xsi="http://www.w3.org/2001/XMLSchema-instance" xsi:schemaLocation="http://www.liquibase.org/xml/ns/dbchangelog http://www.liquibase.org/xml/ns/dbchangelog/dbchangelog-2.0.xsd">
<changeSet author="andy (generated)" id="1311191427300-438">
  <createTable tableName="KSST_NL_USAGE_TYPE">
    <column name="TYPE_KEY" type="java.sql.Types.VARCHAR(255)">
      <constraints nullable="false" primaryKey="true" primaryKeyName="KSST_NL_USAGE_TYPEP1" primaryKeyTablespace="USERS" />
    </column>
    <column name="TYPE_DESC" type="java.sql.Types.VARCHAR(2000)" />
    <column name="EFF_DT" type="java.sql.Types.TIMESTAMP" />
    <column name="EXPIR_DT" type="java.sql.Types.TIMESTAMP" />
    <column name="NAME" type="java.sql.Types.VARCHAR(255)" />
    <column name="OBJ_ID" type="java.sql.Types.VARCHAR(36)" />
    <column name="VER_NBR" type="${bigint.type}(19)" />
  </createTable>
</changeSet>
<changeSet author="andy (generated)" id="1311191427300-439">
  <createTable tableName="KSST_OBJ_TYP_JN_OBJ_SUB_TYP">
    <column name="OBJ_TYPE_ID" type="java.sql.Types.VARCHAR(255)">
      <constraints nullable="false" />
    </column>
    <column name="OBJ_SUB_TYPE_ID" type="java.sql.Types.VARCHAR(255)">
      <constraints nullable="false" />
    </column>
  </createTable>
</changeSet>
<changeSet author="andy (generated)" id="1311191427300-440">
  <createTable tableName="KSST_OBJECT_SUB_TYPE">
    <column name="TYPE_KEY" type="java.sql.Types.VARCHAR(255)">
      <constraints nullable="false" primaryKey="true" primaryKeyName="KSST_OBJECT_SUB_TYPEP1" primaryKeyTablespace="USERS" />
    </column>
    <column name="TYPE_DESC" type="java.sql.Types.VARCHAR(2000)" />
    <column name="EFF_DT" type="java.sql.Types.TIMESTAMP" />
    <column name="EXPIR_DT" type="java.sql.Types.TIMESTAMP" />
    <column name="NAME" type="java.sql.Types.VARCHAR(255)" />
    <column name="OBJ_ID" type="java.sql.Types.VARCHAR(36)" />
    <column name="VER_NBR" type="${bigint.type}(19)" />
  </createTable>
</changeSet>
<changeSet author="andy (generated)" id="1311191427300-441">
  <createTable tableName="KSST_OBJECT_SUB_TYPE_ATTR">
    <column name="ID" type="java.sql.Types.VARCHAR(255)">
      <constraints nullable="false" primaryKey="true" primaryKeyName="KSST_OBJECT_SUB_TYPE_ATTRP1" primaryKeyTablespace="USERS" />
    </column>
    <column name="ATTR_NAME" type="java.sql.Types.VARCHAR(255)" />
    <column name="ATTR_VALUE" type="java.sql.Types.VARCHAR(2000)" />
    <column name="OWNER" type="java.sql.Types.VARCHAR(255)" />
    <column name="OBJ_ID" type="java.sql.Types.VARCHAR(36)" />
    <column name="VER_NBR" type="${bigint.type}(19)" />
  </createTable>
</changeSet>
<changeSet author="andy (generated)" id="1311191427300-442">
  <createTable tableName="KSST_OBJECT_TYPE">
    <column name="TYPE_KEY" type="java.sql.Types.VARCHAR(255)">
      <constraints nullable="false" primaryKey="true" primaryKeyName="KSST_OBJECT_TYPEP1" primaryKeyTablespace="USERS" />
    </column>
    <column name="TYPE_DESC" type="java.sql.Types.VARCHAR(2000)" />
    <column name="EFF_DT" type="java.sql.Types.TIMESTAMP" />
    <column name="EXPIR_DT" type="java.sql.Types.TIMESTAMP" />
    <column name="NAME" type="java.sql.Types.VARCHAR(255)" />
    <column name="OBJ_ID" type="java.sql.Types.VARCHAR(36)" />
    <column name="VER_NBR" type="${bigint.type}(19)" />
  </createTable>
</changeSet>
<changeSet author="andy (generated)" id="1311191427300-443">
  <createTable tableName="KSST_OBJECT_TYPE_ATTR">
    <column name="ID" type="java.sql.Types.VARCHAR(255)">
      <constraints nullable="false" primaryKey="true" primaryKeyName="KSST_OBJECT_TYPE_ATTRP1" primaryKeyTablespace="USERS" />
    </column>
    <column name="ATTR_NAME" type="java.sql.Types.VARCHAR(255)" />
    <column name="ATTR_VALUE" type="java.sql.Types.VARCHAR(2000)" />
    <column name="OWNER" type="java.sql.Types.VARCHAR(255)" />
    <column name="OBJ_ID" type="java.sql.Types.VARCHAR(36)" />
    <column name="VER_NBR" type="${bigint.type}(19)" />
  </createTable>
</changeSet>
<changeSet author="andy (generated)" id="1311191427300-444">
  <createTable tableName="KSST_RC_JN_RC_FIELD">
    <column name="REQ_COM_ID" type="java.sql.Types.VARCHAR(255)">
      <constraints nullable="false" />
    </column>
    <column name="REQ_COM_FIELD_ID" type="java.sql.Types.VARCHAR(255)">
      <constraints nullable="false" />
    </column>
  </createTable>
</changeSet>
<changeSet author="andy (generated)" id="1311191427300-445">
  <createTable tableName="KSST_RCTYP_JN_RCFLDTYP">
    <column name="REQ_COMP_TYPE_ID" type="java.sql.Types.VARCHAR(255)">
      <constraints nullable="false" />
    </column>
    <column name="REQ_COMP_FIELD_TYPE_ID" type="java.sql.Types.VARCHAR(255)">
      <constraints nullable="false" />
    </column>
  </createTable>
</changeSet>
<changeSet author="andy (generated)" id="1311191427300-446">
  <createTable tableName="KSST_REF_STMT_REL">
    <column name="ID" type="java.sql.Types.VARCHAR(255)">
      <constraints nullable="false" primaryKey="true" primaryKeyName="KSST_REF_STMT_RELP1" primaryKeyTablespace="USERS" />
    </column>
    <column name="CREATEID" type="java.sql.Types.VARCHAR(255)" />
    <column name="CREATETIME" type="java.sql.Types.TIMESTAMP" />
    <column name="UPDATEID" type="java.sql.Types.VARCHAR(255)" />
    <column name="UPDATETIME" type="java.sql.Types.TIMESTAMP" />
    <column name="VER_NBR" type="${bigint.type}(19)">
      <constraints nullable="false" />
    </column>
    <column name="EFF_DT" type="java.sql.Types.TIMESTAMP" />
    <column name="EXPIR_DT" type="java.sql.Types.TIMESTAMP" />
    <column name="REF_OBJ_ID" type="java.sql.Types.VARCHAR(255)" />
    <column name="REF_OBJ_TYPE_KEY" type="java.sql.Types.VARCHAR(255)" />
    <column name="ST" type="java.sql.Types.VARCHAR(255)" />
    <column name="REF_STMT_REL_TYPE_ID" type="java.sql.Types.VARCHAR(255)" />
    <column name="STMT_ID" type="java.sql.Types.VARCHAR(255)" />
    <column name="OBJ_ID" type="java.sql.Types.VARCHAR(36)" />
  </createTable>
</changeSet>
<changeSet author="andy (generated)" id="1311191427300-447">
  <createTable tableName="KSST_REF_STMT_REL_ATTR">
    <column name="ID" type="java.sql.Types.VARCHAR(255)">
      <constraints nullable="false" primaryKey="true" primaryKeyName="KSST_REF_STMT_REL_ATTRP1" primaryKeyTablespace="USERS" />
    </column>
    <column name="ATTR_NAME" type="java.sql.Types.VARCHAR(255)" />
    <column name="ATTR_VALUE" type="java.sql.Types.VARCHAR(2000)" />
    <column name="OWNER" type="java.sql.Types.VARCHAR(255)" />
    <column name="OBJ_ID" type="java.sql.Types.VARCHAR(36)" />
    <column name="VER_NBR" type="${bigint.type}(19)" />
  </createTable>
</changeSet>
<changeSet author="andy (generated)" id="1311191427300-448">
  <createTable tableName="KSST_REF_STMT_REL_TYPE">
    <column name="TYPE_KEY" type="java.sql.Types.VARCHAR(255)">
      <constraints nullable="false" primaryKey="true" primaryKeyName="KSST_REF_STMT_REL_TYPEP1" primaryKeyTablespace="USERS" />
    </column>
    <column name="TYPE_DESC" type="java.sql.Types.VARCHAR(2000)" />
    <column name="EFF_DT" type="java.sql.Types.TIMESTAMP" />
    <column name="EXPIR_DT" type="java.sql.Types.TIMESTAMP" />
    <column name="NAME" type="java.sql.Types.VARCHAR(255)" />
    <column name="OBJ_ID" type="java.sql.Types.VARCHAR(36)" />
    <column name="VER_NBR" type="${bigint.type}(19)" />
  </createTable>
</changeSet>
<changeSet author="andy (generated)" id="1311191427300-449">
  <createTable tableName="KSST_REF_STMT_REL_TYPE_ATTR">
    <column name="ID" type="java.sql.Types.VARCHAR(255)">
      <constraints nullable="false" primaryKey="true" primaryKeyName="KSST_REF_STMT_REL_TYPE_ATTRP1" primaryKeyTablespace="USERS" />
    </column>
    <column name="ATTR_NAME" type="java.sql.Types.VARCHAR(255)" />
    <column name="ATTR_VALUE" type="java.sql.Types.VARCHAR(2000)" />
    <column name="OWNER" type="java.sql.Types.VARCHAR(255)" />
    <column name="OBJ_ID" type="java.sql.Types.VARCHAR(36)" />
    <column name="VER_NBR" type="${bigint.type}(19)" />
  </createTable>
</changeSet>
<changeSet author="andy (generated)" id="1311191427300-450">
  <createTable tableName="KSST_REQ_COM">
    <column name="ID" type="java.sql.Types.VARCHAR(255)">
      <constraints nullable="false" primaryKey="true" primaryKeyName="KSST_REQ_COMP1" primaryKeyTablespace="USERS" />
    </column>
    <column name="CREATEID" type="java.sql.Types.VARCHAR(255)" />
    <column name="CREATETIME" type="java.sql.Types.TIMESTAMP" />
    <column name="UPDATEID" type="java.sql.Types.VARCHAR(255)" />
    <column name="UPDATETIME" type="java.sql.Types.TIMESTAMP" />
    <column name="VER_NBR" type="${bigint.type}(19)">
      <constraints nullable="false" />
    </column>
    <column name="EFF_DT" type="java.sql.Types.TIMESTAMP" />
    <column name="EXPIR_DT" type="java.sql.Types.TIMESTAMP" />
    <column name="ST" type="java.sql.Types.VARCHAR(255)" />
    <column name="RT_DESCR_ID" type="java.sql.Types.VARCHAR(255)" />
    <column name="REQ_COM_TYPE_ID" type="java.sql.Types.VARCHAR(255)" />
    <column name="OBJ_ID" type="java.sql.Types.VARCHAR(36)" />
  </createTable>
</changeSet>
<changeSet author="andy (generated)" id="1311191427300-451">
  <createTable tableName="KSST_REQ_COM_FIELD">
    <column name="ID" type="java.sql.Types.VARCHAR(255)">
      <constraints nullable="false" primaryKey="true" primaryKeyName="KSST_REQ_COM_FIELDP1" primaryKeyTablespace="USERS" />
    </column>
    <column name="REQ_COM_FIELD_TYPE" type="java.sql.Types.VARCHAR(255)" />
    <column name="VALUE" type="java.sql.Types.VARCHAR(255)" />
    <column name="OBJ_ID" type="java.sql.Types.VARCHAR(36)" />
    <column name="VER_NBR" type="${bigint.type}(19)" />
  </createTable>
</changeSet>
<changeSet author="andy (generated)" id="1311191427300-452">
  <createTable tableName="KSST_REQ_COM_FIELD_TYPE">
    <column name="ID" type="java.sql.Types.VARCHAR(255)">
      <constraints nullable="false" primaryKey="true" primaryKeyName="KSST_REQ_COM_FIELD_TYPEP1" primaryKeyTablespace="USERS" />
    </column>
    <column name="DATA_TYPE" type="java.sql.Types.VARCHAR(255)">
      <constraints nullable="false" />
    </column>
    <column name="DESCR" type="java.sql.Types.VARCHAR(255)">
      <constraints nullable="false" />
    </column>
    <column name="INVALID_CHARS" type="java.sql.Types.VARCHAR(255)" />
    <column name="MAX_LENGTH" type="${integer.type}(10)" />
    <column name="MAX_OCCURS" type="${integer.type}(10)" />
    <column name="MAX_VALUE" type="java.sql.Types.VARCHAR(255)" />
    <column name="MIN_LENGTH" type="${integer.type}(10)" />
    <column name="MIN_OCCURS" type="${integer.type}(10)" />
    <column name="MIN_VALUE" type="java.sql.Types.VARCHAR(255)" />
    <column name="NAME" type="java.sql.Types.VARCHAR(255)">
      <constraints nullable="false" />
    </column>
    <column name="READ_ONLY" type="BOOLEAN">
      <constraints nullable="false" />
    </column>
    <column name="VALID_CHARS" type="java.sql.Types.VARCHAR(255)" />
    <column name="OBJ_ID" type="java.sql.Types.VARCHAR(36)" />
    <column name="VER_NBR" type="${bigint.type}(19)" />
  </createTable>
</changeSet>
<changeSet author="andy (generated)" id="1311191427300-453">
  <createTable tableName="KSST_REQ_COM_TYPE">
    <column name="TYPE_KEY" type="java.sql.Types.VARCHAR(255)">
      <constraints nullable="false" primaryKey="true" primaryKeyName="KSST_REQ_COM_TYPEP1" primaryKeyTablespace="USERS" />
    </column>
    <column name="TYPE_DESC" type="java.sql.Types.VARCHAR(2000)" />
    <column name="EFF_DT" type="java.sql.Types.TIMESTAMP" />
    <column name="EXPIR_DT" type="java.sql.Types.TIMESTAMP" />
    <column name="NAME" type="java.sql.Types.VARCHAR(255)" />
    <column name="OBJ_ID" type="java.sql.Types.VARCHAR(36)" />
    <column name="VER_NBR" type="${bigint.type}(19)" />
  </createTable>
</changeSet>
<changeSet author="andy (generated)" id="1311191427300-454">
  <createTable tableName="KSST_REQ_COM_TYPE_ATTR">
    <column name="ID" type="java.sql.Types.VARCHAR(255)">
      <constraints nullable="false" primaryKey="true" primaryKeyName="KSST_REQ_COM_TYPE_ATTRP1" primaryKeyTablespace="USERS" />
    </column>
    <column name="ATTR_NAME" type="java.sql.Types.VARCHAR(255)" />
    <column name="ATTR_VALUE" type="java.sql.Types.VARCHAR(2000)" />
    <column name="OWNER" type="java.sql.Types.VARCHAR(255)" />
    <column name="OBJ_ID" type="java.sql.Types.VARCHAR(36)" />
    <column name="VER_NBR" type="${bigint.type}(19)" />
  </createTable>
</changeSet>
<changeSet author="andy (generated)" id="1311191427300-455">
  <createTable tableName="KSST_REQ_COM_TYPE_NL_TMPL">
    <column name="ID" type="java.sql.Types.VARCHAR(255)">
      <constraints nullable="false" primaryKey="true" primaryKeyName="KSST_REQ_COM_TYPE_NL_TMPLP1" primaryKeyTablespace="USERS" />
    </column>
    <column name="ATTR_NAME" type="java.sql.Types.VARCHAR(255)" />
    <column name="ATTR_VALUE" type="java.sql.Types.VARCHAR(2000)" />
    <column name="LANGUAGE" type="java.sql.Types.VARCHAR(2)" />
    <column name="NL_USUAGE_TYPE_KEY" type="java.sql.Types.VARCHAR(255)" />
    <column name="TEMPLATE" type="java.sql.Types.VARCHAR(2000)" />
    <column name="OWNER" type="java.sql.Types.VARCHAR(255)" />
    <column name="OBJ_ID" type="java.sql.Types.VARCHAR(36)" />
    <column name="VER_NBR" type="${bigint.type}(19)" />
  </createTable>
</changeSet>
<changeSet author="andy (generated)" id="1311191427300-456">
  <createTable tableName="KSST_RICH_TEXT_T">
    <column name="ID" type="java.sql.Types.VARCHAR(255)">
      <constraints nullable="false" primaryKey="true" primaryKeyName="KSST_RICH_TEXT_TP1" primaryKeyTablespace="USERS" />
    </column>
    <column name="FORMATTED" type="java.sql.Types.VARCHAR(2000)" />
    <column name="PLAIN" type="java.sql.Types.VARCHAR(2000)" />
    <column name="OBJ_ID" type="java.sql.Types.VARCHAR(36)" />
    <column name="VER_NBR" type="${bigint.type}(19)" />
  </createTable>
</changeSet>
<changeSet author="andy (generated)" id="1311191427300-457">
  <createTable tableName="KSST_RSTMT_RTYP_JN_OSUB_TYP">
    <column name="REF_STMT_REL_TYPE_ID" type="java.sql.Types.VARCHAR(255)">
      <constraints nullable="false" />
    </column>
    <column name="OBJ_SUB_TYPE_ID" type="java.sql.Types.VARCHAR(255)">
      <constraints nullable="false" />
    </column>
  </createTable>
</changeSet>
<changeSet author="andy (generated)" id="1311191427300-458">
  <createTable tableName="KSST_RSTMT_RTYP_JN_STMT_TYP">
    <column name="REF_STMT_REL_TYPE_ID" type="java.sql.Types.VARCHAR(255)">
      <constraints nullable="false" />
    </column>
    <column name="STMT_TYPE_ID" type="java.sql.Types.VARCHAR(255)">
      <constraints nullable="false" />
    </column>
  </createTable>
</changeSet>
<changeSet author="andy (generated)" id="1311191427300-459">
  <createTable tableName="KSST_STMT">
    <column name="ID" type="java.sql.Types.VARCHAR(255)">
      <constraints nullable="false" primaryKey="true" primaryKeyName="KSST_STMTP1" primaryKeyTablespace="USERS" />
    </column>
    <column name="CREATEID" type="java.sql.Types.VARCHAR(255)" />
    <column name="CREATETIME" type="java.sql.Types.TIMESTAMP" />
    <column name="UPDATEID" type="java.sql.Types.VARCHAR(255)" />
    <column name="UPDATETIME" type="java.sql.Types.TIMESTAMP" />
    <column name="VER_NBR" type="${bigint.type}(19)">
      <constraints nullable="false" />
    </column>
    <column name="NAME" type="java.sql.Types.VARCHAR(255)" />
    <column name="OPERATOR" type="java.sql.Types.VARCHAR(255)" />
    <column name="ST" type="java.sql.Types.VARCHAR(255)" />
    <column name="RT_DESCR_ID" type="java.sql.Types.VARCHAR(255)" />
    <column name="STMT_TYPE_ID" type="java.sql.Types.VARCHAR(255)" />
    <column name="OBJ_ID" type="java.sql.Types.VARCHAR(36)" />
  </createTable>
</changeSet>
<changeSet author="andy (generated)" id="1311191427300-460">
  <createTable tableName="KSST_STMT_ATTR">
    <column name="ID" type="java.sql.Types.VARCHAR(255)">
      <constraints nullable="false" primaryKey="true" primaryKeyName="KSST_STMT_ATTRP1" primaryKeyTablespace="USERS" />
    </column>
    <column name="ATTR_NAME" type="java.sql.Types.VARCHAR(255)" />
    <column name="ATTR_VALUE" type="java.sql.Types.VARCHAR(2000)" />
    <column name="OWNER" type="java.sql.Types.VARCHAR(255)" />
    <column name="OBJ_ID" type="java.sql.Types.VARCHAR(36)" />
    <column name="VER_NBR" type="${bigint.type}(19)" />
  </createTable>
</changeSet>
<changeSet author="andy (generated)" id="1311191427300-461">
  <createTable tableName="KSST_STMT_JN_REQ_COM">
    <column name="STMT_ID" type="java.sql.Types.VARCHAR(255)">
      <constraints nullable="false" />
    </column>
    <column name="REQ_COM_ID" type="java.sql.Types.VARCHAR(255)">
      <constraints nullable="false" />
    </column>
  </createTable>
</changeSet>
<changeSet author="andy (generated)" id="1311191427300-462">
  <createTable tableName="KSST_STMT_JN_STMT">
    <column name="STMT_ID" type="java.sql.Types.VARCHAR(255)">
      <constraints nullable="false" />
    </column>
    <column name="CHLD_STMT_ID" type="java.sql.Types.VARCHAR(255)">
      <constraints nullable="false" />
    </column>
  </createTable>
</changeSet>
<changeSet author="andy (generated)" id="1311191427300-463">
  <createTable tableName="KSST_STMT_TYP_JN_RC_TYP">
    <column name="ID" type="java.sql.Types.VARCHAR(255)">
      <constraints nullable="false" primaryKey="true" primaryKeyName="KSST_STMT_TYP_JN_RC_TYPP1" primaryKeyTablespace="USERS" />
    </column>
    <column name="OBJ_ID" type="java.sql.Types.VARCHAR(36)" />
    <column name="VER_NBR" type="${bigint.type}(19)" />
    <column name="REQ_COM_TYPE_ID" type="java.sql.Types.VARCHAR(255)" />
    <column name="SORT_ORDER" type="${integer.type}(10)" />
    <column name="STMT_TYPE_ID" type="java.sql.Types.VARCHAR(255)" />
  </createTable>
</changeSet>
<changeSet author="andy (generated)" id="1311191427300-464">
  <createTable tableName="KSST_STMT_TYP_JN_STMT_TYP">
    <column name="ID" type="java.sql.Types.VARCHAR(255)">
      <constraints nullable="false" primaryKey="true" primaryKeyName="KSST_STMT_TYP_JN_STMT_TYPP1" primaryKeyTablespace="USERS" />
    </column>
    <column name="OBJ_ID" type="java.sql.Types.VARCHAR(36)" />
    <column name="VER_NBR" type="${bigint.type}(19)" />
    <column name="CHLD_STMT_TYPE_ID" type="java.sql.Types.VARCHAR(255)" />
    <column name="SORT_ORDER" type="${integer.type}(10)" />
    <column name="STMT_TYPE_ID" type="java.sql.Types.VARCHAR(255)" />
  </createTable>
</changeSet>
<changeSet author="andy (generated)" id="1311191427300-465">
  <createTable tableName="KSST_STMT_TYPE">
    <column name="TYPE_KEY" type="java.sql.Types.VARCHAR(255)">
      <constraints nullable="false" primaryKey="true" primaryKeyName="KSST_STMT_TYPEP1" primaryKeyTablespace="USERS" />
    </column>
    <column name="TYPE_DESC" type="java.sql.Types.VARCHAR(2000)" />
    <column name="EFF_DT" type="java.sql.Types.TIMESTAMP" />
    <column name="EXPIR_DT" type="java.sql.Types.TIMESTAMP" />
    <column name="NAME" type="java.sql.Types.VARCHAR(255)" />
    <column name="OBJ_ID" type="java.sql.Types.VARCHAR(36)" />
    <column name="VER_NBR" type="${bigint.type}(19)" />
  </createTable>
</changeSet>
<changeSet author="andy (generated)" id="1311191427300-466">
  <createTable tableName="KSST_STMT_TYPE_ATTR">
    <column name="ID" type="java.sql.Types.VARCHAR(255)">
      <constraints nullable="false" primaryKey="true" primaryKeyName="KSST_STMT_TYPE_ATTRP1" primaryKeyTablespace="USERS" />
    </column>
    <column name="ATTR_NAME" type="java.sql.Types.VARCHAR(255)" />
    <column name="ATTR_VALUE" type="java.sql.Types.VARCHAR(2000)" />
    <column name="OWNER" type="java.sql.Types.VARCHAR(255)" />
    <column name="OBJ_ID" type="java.sql.Types.VARCHAR(36)" />
    <column name="VER_NBR" type="${bigint.type}(19)" />
  </createTable>
</changeSet>
<changeSet author="andy (generated)" id="1311191427300-467">
  <createTable tableName="KSST_USAGE_TYPE_ATTR">
    <column name="ID" type="java.sql.Types.VARCHAR(255)">
      <constraints nullable="false" primaryKey="true" primaryKeyName="KSST_USAGE_TYPE_ATTRP1" primaryKeyTablespace="USERS" />
    </column>
    <column name="ATTR_NAME" type="java.sql.Types.VARCHAR(255)" />
    <column name="ATTR_VALUE" type="java.sql.Types.VARCHAR(2000)" />
    <column name="OWNER" type="java.sql.Types.VARCHAR(255)" />
    <column name="OBJ_ID" type="java.sql.Types.VARCHAR(36)" />
    <column name="VER_NBR" type="${bigint.type}(19)" />
  </createTable>
</changeSet>
</databaseChangeLog>
